subprocess_middleware/__init__.py
subprocess_middleware/response.py
subprocess_middleware/tests/__init__.py
subprocess_middleware/tests/conftest.py
subprocess_middleware/tests/test_subprocess_middleware.py
subprocess_middleware/tests/testing.py
subprocess_middleware/tests/testing_transform.py
subprocess_middleware/tween.py
subprocess_middleware/worker.py
subprocess_middleware/wsgi.py
subprocess_middleware_c4-0.4.0.0b1.dist-info/LICENSE.txt
subprocess_middleware_c4-0.4.0.0b1.dist-info/WHEEL
subprocess_middleware_c4-0.4.0.0b1.dist-info/METADATA
subprocess_middleware_c4-0.4.0.0b1.dist-info/RECORD
